aiymakerkit/__init__.py
aiymakerkit/audio.py
aiymakerkit/ring_buffer.py
aiymakerkit/utils.py
aiymakerkit/vision.py
aiymakerkit-1.0.0.dist-info/LICENSE
aiymakerkit-1.0.0.dist-info/METADATA
aiymakerkit-1.0.0.dist-info/WHEEL
aiymakerkit-1.0.0.dist-info/top_level.txt
aiymakerkit-1.0.0.dist-info/RECORD
