Metadata-Version: 2.1
Name: aiymakerkit
Version: 1.0.0
Summary: Simple API for ML inferencing with TF Lite and Coral Edge TPU
Home-page: https://github.com/google-coral/aiy-maker-kit
Author: Coral
Author-email: coral-support@google.com
License: Apache 2
License-File: LICENSE
Requires-Dist: pycoral (>=2.0.0)
Requires-Dist: tflite-support (>=0.3.1)
Requires-Dist: tflite-runtime
Requires-Dist: pyaudio
Requires-Dist: opencv-python
Requires-Dist: numpy
